kmService/__init__.py
kmService/km_service.py
kmService/km_service_builder.py
kmService/models.py
kmService/py.typed
kmService/uitils/__init__.py
kmService/uitils/log.py
kmService/uitils/shapely_geojson.py
kmService/uitils/shapely_helpers.py
kmService/uitils/shapleyTools.py
kmservice-0.0.1.dist-info/METADATA
kmservice-0.0.1.dist-info/WHEEL
kmservice-0.0.1.dist-info/licenses/LICENSE.md
kmservice-0.0.1.dist-info/RECORD
