Metadata-Version: 2.1
Name: kmService
Version: 0.0.1
Project-URL: Documentation, https://Hazedd.github.io/kmService/
Project-URL: Source, https://github.com/Hazedd/kmService
Author-email: kmService <Hazedd@no-replay.github.com>
License-File: LICENSE.md
Classifier: Programming Language :: Python :: 3 :: Only
Requires-Python: >=3.10
Requires-Dist: arcgisfeaturecache
Requires-Dist: nest-asyncio
Requires-Dist: pyproj
Requires-Dist: rtree
